{
	"id": "com.webos.app.volume",
	"version": "1.0.0",
	"vendor": "LGE-SWP",
	"type": "web",
	"main": "index.html",
	"title": "Enact Volume Control",
	"icon": "icon.png",
	"miniicon": "icon-mini.png",
	"largeIcon": "icon-large.png",
	"uiRevision": 2,
	"requiredPermissions": [
		"all"
	],
	"trustLevel": "trusted",
	"accessibility": {
		"supportsAudioGuidance": true
	},
	"defaultWindowType": "system_ui",
	"noSplashOnLaunch": true,
	"spinnerOnLaunch": false,
	"transparent": true,
	"lockable": false,
	"visible": false
}
